pysofe-0.1.0.dist-info/RECORD
pysofe-0.1.0.dist-info/DESCRIPTION.rst
pysofe-0.1.0.dist-info/top_level.txt
pysofe-0.1.0.dist-info/METADATA
pysofe-0.1.0.dist-info/metadata.json
pysofe-0.1.0.dist-info/WHEEL
pysofe/visualization.py
pysofe/__init__.py
pysofe/utils.py
pysofe/elements/__init__.py
pysofe/elements/base.py
pysofe/elements/simple/__init__.py
pysofe/elements/simple/lagrange.py
pysofe/pde/conditions.py
pysofe/pde/poisson.py
pysofe/pde/__init__.py
pysofe/pde/base.py
pysofe/meshes/reference_map.py
pysofe/meshes/topology.py
pysofe/meshes/geometry.py
pysofe/meshes/__init__.py
pysofe/meshes/mesh.py
pysofe/meshes/refinements/uniform.py
pysofe/meshes/refinements/__init__.py
pysofe/quadrature/__init__.py
pysofe/quadrature/base.py
pysofe/quadrature/gaussian.py
pysofe/spaces/operators.py
pysofe/spaces/functions.py
pysofe/spaces/manager.py
pysofe/spaces/__init__.py
pysofe/spaces/space.py
